[
 
  {
    "imgSrc": "https://images.pexels.com/photos/4381392/pexels-photo-4381392.jpeg?auto=compress&cs=tinysrgb&dpr=1&w=500" ,
    "title": "HEY HOY! ",
    "text": " Lorem ipsuim dolor sit amet, consectetur adipiscin elit. Pellentesque nec nunc sit amet nibh vulputate  hendrerit. Curabitur placerat augue eu ligula  volutpat, eu consectetur est sollicitudin.  ",
    "content": "+200,000 " ,
    "content1": " +$35,000",
    "content2": " +150",
    "par": "STREAMS",
    "par1": "REVENUE ",
    "par2": "COLLABS "
  },
{
    "imgSrc": "https://images.pexels.com/photos/4381392/pexels-photo-4381392.jpeg?auto=compress&cs=tinysrgb&dpr=1&w=500" ,
    "title": "FUCKING AMAZING! ",
    "text": " Lorem ipsuim dolor sit amet, consectetur adipiscin elit. Pellentesque nec nunc sit amet nibh vulputate  hendrerit. Curabitur placerat augue eu ligula  volutpat, eu consectetur est sollicitudin.  ",
    "content": "+200,000 " ,
    "content1": " +$35,000",
    "content2": " +150",
    "par": "STREAMS",
    "par1": "REVENUE ",
    "par2": "COLLABS "
  },
  {
    "imgSrc": "https://images.pexels.com/photos/4381392/pexels-photo-4381392.jpeg?auto=compress&cs=tinysrgb&dpr=1&w=500" ,
    "title": " RAPUCLT AWW ",
    "text": " Lorem ipsuim dolor sit amet, consectetur adipiscin elit. Pellentesque nec nunc sit amet nibh vulputate  hendrerit. Curabitur placerat augue eu ligula  volutpat, eu consectetur est sollicitudin.  ",
    "content": "+200,000 " ,
    "content1": " +$35,000",
    "content2": " +150",
    "par": "STREAMS",
    "par1": "REVENUE ",
    "par2": "COLLABS "
  }


]